{
	"id": "PY8Yro1faKLRUsL",
	"json": "{\"id\":\"PY8Yro1faKLRUsL\",\"url\":\"https://www.smartone.com/tc/home/mobile-service-plans/listing/detail?group=retiree&plan=retiree_8g\",\"uniqueKey\":\"https://www.smartone.com/tc/home/mobile-service-plans/listing/detail?group=retiree&plan=retiree_8g\",\"method\":\"GET\",\"noRetry\":false,\"retryCount\":0,\"errorMessages\":[],\"headers\":{},\"userData\":{}}",
	"method": "GET",
	"orderNo": 1658642763842,
	"retryCount": 0,
	"uniqueKey": "https://www.smartone.com/tc/home/mobile-service-plans/listing/detail?group=retiree&plan=retiree_8g",
	"url": "https://www.smartone.com/tc/home/mobile-service-plans/listing/detail?group=retiree&plan=retiree_8g"
}