{
	"id": "rLTclhveDNpcdmw",
	"json": "{\"id\":\"rLTclhveDNpcdmw\",\"url\":\"https://media.smartone.com/video/brand/leave_home_safe_video.mp4\",\"uniqueKey\":\"https://media.smartone.com/video/brand/leave_home_safe_video.mp4\",\"method\":\"GET\",\"noRetry\":false,\"retryCount\":0,\"errorMessages\":[],\"headers\":{},\"userData\":{}}",
	"method": "GET",
	"orderNo": 1658642753595,
	"retryCount": 0,
	"uniqueKey": "https://media.smartone.com/video/brand/leave_home_safe_video.mp4",
	"url": "https://media.smartone.com/video/brand/leave_home_safe_video.mp4"
}